{
  "type": "FeatureCollection",
  "features": [
    {
      "type": "Feature",
      "geometry": {
        "type": "Point",
        "coordinates": [
          34.840833,
          31.244722
        ]
      },
      "properties": {
        "name": "Beersheba 2 / Tel Beer Sheva",
        "description": "another name for Beersheba 1",
        "styleUrl": "#landpoint",
        "icon-scale": 0.75,
        "icon": "https://maps.google.com/mapfiles/kml/paddle/red-circle.png"
      }
    },
    {
      "type": "Feature",
      "geometry": {
        "type": "Point",
        "coordinates": [
          34.793078,
          31.237225
        ]
      },
      "properties": {
        "name": "Beersheba 2 / Bir es Seba",
        "description": "another name for Beersheba 1",
        "styleUrl": "#landpoint",
        "icon-scale": 0.75,
        "icon": "https://maps.google.com/mapfiles/kml/paddle/red-circle.png"
      }
    },
    {
      "type": "Feature",
      "geometry": {
        "type": "Point",
        "coordinates": [
          34.793078,
          31.237225
        ]
      },
      "properties": {
        "name": "Beersheba 2 / Bir es Seba",
        "styleUrl": "#landpoint",
        "icon-scale": 0.75,
        "icon": "https://maps.google.com/mapfiles/kml/paddle/red-circle.png"
      }
    }
  ]
}