{
  "type": "FeatureCollection",
  "features": [
    {
      "type": "Feature",
      "geometry": {
        "type": "Point",
        "coordinates": [
          34.98714,
          31.86981
        ]
      },
      "properties": {
        "name": "Shaalbon / Salbit",
        "description": "another name for Shaalbim",
        "styleUrl": "#landpoint",
        "icon-scale": 0.75,
        "icon": "https://maps.google.com/mapfiles/kml/paddle/red-circle.png"
      }
    },
    {
      "type": "Feature",
      "geometry": {
        "type": "Point",
        "coordinates": [
          35.3725,
          32.354167
        ]
      },
      "properties": {
        "name": "Shaalbon / Khirbet Salhab",
        "description": "another name for Shaalbim",
        "styleUrl": "#landpoint",
        "icon-scale": 0.75,
        "icon": "https://maps.google.com/mapfiles/kml/paddle/red-circle.png"
      }
    }
  ]
}