{
  "type": "FeatureCollection",
  "features": [
    {
      "type": "Feature",
      "geometry": {
        "type": "Point",
        "coordinates": [
          43.1528,
          36.3594
        ]
      },
      "properties": {
        "name": "Rehoboth-Ir / in Nineveh",
        "styleUrl": "#landpoint",
        "icon-scale": 0.75,
        "icon": "https://maps.google.com/mapfiles/kml/paddle/red-circle.png"
      }
    },
    {
      "type": "Feature",
      "geometry": {
        "type": "Point",
        "coordinates": [
          43.1528,
          36.3594
        ]
      },
      "properties": {
        "name": "Rehoboth-Ir / Nineveh",
        "description": "another name for Nineveh",
        "styleUrl": "#landpoint",
        "icon-scale": 0.75,
        "icon": "https://maps.google.com/mapfiles/kml/paddle/red-circle.png"
      }
    },
    {
      "type": "Feature",
      "geometry": {
        "type": "Point",
        "coordinates": [
          43.2625,
          35.456667
        ]
      },
      "properties": {
        "name": "Rehoboth-Ir / Assur",
        "description": "another name for Asshur",
        "styleUrl": "#landpoint",
        "icon-scale": 0.75,
        "icon": "https://maps.google.com/mapfiles/kml/paddle/red-circle.png"
      }
    },
    {
      "type": "Feature",
      "geometry": {
        "type": "Point",
        "coordinates": [
          43.328889,
          36.098056
        ]
      },
      "properties": {
        "name": "Rehoboth-Ir / in Nimrud",
        "description": "in Calah",
        "styleUrl": "#landpoint",
        "icon-scale": 0.75,
        "icon": "https://maps.google.com/mapfiles/kml/paddle/red-circle.png"
      }
    }
  ]
}