{
  "type": "FeatureCollection",
  "features": [
    {
      "type": "Feature",
      "geometry": {
        "type": "Point",
        "coordinates": [
          35.234167,
          31.776667
        ]
      },
      "properties": {
        "name": "West Gate / in Jerusalem",
        "description": "another name for Shallecheth",
        "styleUrl": "#landpoint",
        "icon-scale": 0.75,
        "icon": "https://maps.google.com/mapfiles/kml/paddle/red-circle.png"
      }
    },
    {
      "type": "Feature",
      "geometry": {
        "type": "Point",
        "coordinates": [
          35.231839,
          31.776414
        ]
      },
      "properties": {
        "name": "West Gate / Israelite Tower",
        "description": "another name for Shallecheth",
        "styleUrl": "#landpoint",
        "icon-scale": 0.75,
        "icon": "https://maps.google.com/mapfiles/kml/paddle/red-circle.png"
      }
    },
    {
      "type": "Feature",
      "geometry": {
        "type": "Point",
        "coordinates": [
          35.234167,
          31.776667
        ]
      },
      "properties": {
        "name": "West Gate / in Jerusalem",
        "styleUrl": "#landpoint",
        "icon-scale": 0.75,
        "icon": "https://maps.google.com/mapfiles/kml/paddle/red-circle.png"
      }
    },
    {
      "type": "Feature",
      "geometry": {
        "type": "Point",
        "coordinates": [
          35.234167,
          31.776667
        ]
      },
      "properties": {
        "name": "West Gate / in Jerusalem",
        "description": "another name for the Parbar",
        "styleUrl": "#landpoint",
        "icon-scale": 0.75,
        "icon": "https://maps.google.com/mapfiles/kml/paddle/red-circle.png"
      }
    }
  ]
}