{
  "type": "FeatureCollection",
  "features": [
    {
      "type": "Feature",
      "geometry": {
        "type": "Point",
        "coordinates": [
          35.234167,
          31.776667
        ]
      },
      "properties": {
        "name": "Potsherd Gate / in Jerusalem",
        "styleUrl": "#landpoint",
        "icon-scale": 0.75,
        "icon": "https://maps.google.com/mapfiles/kml/paddle/red-circle.png"
      }
    },
    {
      "type": "Feature",
      "geometry": {
        "type": "Point",
        "coordinates": [
          35.234167,
          31.776667
        ]
      },
      "properties": {
        "name": "Potsherd Gate / in Jerusalem",
        "description": "another name for the Dung Gate",
        "styleUrl": "#landpoint",
        "icon-scale": 0.75,
        "icon": "https://maps.google.com/mapfiles/kml/paddle/red-circle.png"
      }
    },
    {
      "type": "Feature",
      "geometry": {
        "type": "Point",
        "coordinates": [
          35.234167,
          31.776667
        ]
      },
      "properties": {
        "name": "Potsherd Gate / in Jerusalem",
        "description": "another name for the East Gate",
        "styleUrl": "#landpoint",
        "icon-scale": 0.75,
        "icon": "https://maps.google.com/mapfiles/kml/paddle/red-circle.png"
      }
    },
    {
      "type": "Feature",
      "geometry": {
        "type": "Point",
        "coordinates": [
          35.234167,
          31.776667
        ]
      },
      "properties": {
        "name": "Potsherd Gate / in Jerusalem",
        "description": "another name for the Valley Gate",
        "styleUrl": "#landpoint",
        "icon-scale": 0.75,
        "icon": "https://maps.google.com/mapfiles/kml/paddle/red-circle.png"
      }
    },
    {
      "type": "Feature",
      "geometry": {
        "type": "Point",
        "coordinates": [
          35.234998,
          31.774071
        ]
      },
      "properties": {
        "name": "Potsherd Gate / Crowfoot and Fitzgerald excavation site",
        "description": "another name for the Valley Gate",
        "styleUrl": "#landpoint",
        "icon-scale": 0.75,
        "icon": "https://maps.google.com/mapfiles/kml/paddle/red-circle.png"
      }
    },
    {
      "type": "Feature",
      "geometry": {
        "type": "Point",
        "coordinates": [
          35.227694,
          31.776528
        ]
      },
      "properties": {
        "name": "Potsherd Gate / Jaffa Gate",
        "description": "another name for the Valley Gate",
        "styleUrl": "#landpoint",
        "icon-scale": 0.75,
        "icon": "https://maps.google.com/mapfiles/kml/paddle/red-circle.png"
      }
    }
  ]
}