{
  "type": "FeatureCollection",
  "features": [
    {
      "type": "Feature",
      "geometry": {
        "type": "Point",
        "coordinates": [
          43.711389,
          16.871944
        ]
      },
      "properties": {
        "name": "Parvaim / Farwah",
        "styleUrl": "#landpoint",
        "icon-scale": 0.75,
        "icon": "https://maps.google.com/mapfiles/kml/paddle/red-circle.png"
      }
    },
    {
      "type": "Feature",
      "geometry": {
        "type": "Point",
        "coordinates": [
          42.72595,
          25.70934
        ]
      },
      "properties": {
        "name": "Parvaim / Saq el Farwein",
        "styleUrl": "#landpoint",
        "icon-scale": 0.75,
        "icon": "https://maps.google.com/mapfiles/kml/paddle/red-circle.png"
      }
    },
    {
      "type": "Feature",
      "geometry": {
        "type": "Point",
        "coordinates": [
          54.130865,
          17.006157
        ]
      },
      "properties": {
        "name": "Parvaim / Al Baleed",
        "description": "another name for Sephar",
        "styleUrl": "#landpoint",
        "icon-scale": 0.75,
        "icon": "https://maps.google.com/mapfiles/kml/paddle/red-circle.png"
      }
    },
    {
      "type": "Feature",
      "geometry": {
        "type": "Point",
        "coordinates": [
          44.402874,
          14.213898
        ]
      },
      "properties": {
        "name": "Parvaim / Zafar",
        "description": "another name for Sephar",
        "styleUrl": "#landpoint",
        "icon-scale": 0.75,
        "icon": "https://maps.google.com/mapfiles/kml/paddle/red-circle.png"
      }
    }
  ]
}