{
  "type": "FeatureCollection",
  "features": [
    {
      "type": "Feature",
      "geometry": {
        "type": "Point",
        "coordinates": [
          36.61899,
          32.75616
        ]
      },
      "properties": {
        "name": "Nobah 1 / Qanawat",
        "description": "another name for Kenath",
        "styleUrl": "#landpoint",
        "icon-scale": 0.75,
        "icon": "https://maps.google.com/mapfiles/kml/paddle/red-circle.png"
      }
    },
    {
      "type": "Feature",
      "geometry": {
        "type": "Point",
        "coordinates": [
          36.348611,
          32.686111
        ]
      },
      "properties": {
        "name": "Nobah 1 / Krak Canatha",
        "description": "another name for Kenath",
        "styleUrl": "#landpoint",
        "icon-scale": 0.75,
        "icon": "https://maps.google.com/mapfiles/kml/paddle/red-circle.png"
      }
    }
  ]
}