{
  "type": "FeatureCollection",
  "features": [
    {
      "type": "Feature",
      "geometry": {
        "type": "Point",
        "coordinates": [
          31.963611,
          30.5475
        ]
      },
      "properties": {
        "name": "Pithom / Tell er Retaba",
        "styleUrl": "#landpoint",
        "icon-scale": 0.75,
        "icon": "https://maps.google.com/mapfiles/kml/paddle/red-circle.png"
      }
    },
    {
      "type": "Feature",
      "geometry": {
        "type": "Point",
        "coordinates": [
          32.099,
          30.5527
        ]
      },
      "properties": {
        "name": "Pithom / Tell el Maskhuta",
        "styleUrl": "#landpoint",
        "icon-scale": 0.75,
        "icon": "https://maps.google.com/mapfiles/kml/paddle/red-circle.png"
      }
    },
    {
      "type": "Feature",
      "geometry": {
        "type": "Point",
        "coordinates": [
          31.3075,
          30.129444
        ]
      },
      "properties": {
        "name": "Pithom / Ain Shams",
        "description": "another name for Heliopolis",
        "styleUrl": "#landpoint",
        "icon-scale": 0.75,
        "icon": "https://maps.google.com/mapfiles/kml/paddle/red-circle.png"
      }
    }
  ]
}