{
  "type": "FeatureCollection",
  "features": [
    {
      "type": "Feature",
      "geometry": {
        "type": "Point",
        "coordinates": [
          35.310556,
          32.788056
        ]
      },
      "properties": {
        "name": "Dimnah / Rumana",
        "description": "another name for Rimmon 3",
        "styleUrl": "#landpoint",
        "icon-scale": 0.75,
        "icon": "https://maps.google.com/mapfiles/kml/paddle/red-circle.png"
      }
    },
    {
      "type": "Feature",
      "geometry": {
        "type": "Point",
        "coordinates": [
          35.459722,
          32.799722
        ]
      },
      "properties": {
        "name": "Dimnah / Qarn Hattin",
        "description": "another name for Rimmon 3",
        "styleUrl": "#landpoint",
        "icon-scale": 0.75,
        "icon": "https://maps.google.com/mapfiles/kml/paddle/red-circle.png"
      }
    },
    {
      "type": "Feature",
      "geometry": {
        "type": "Point",
        "coordinates": [
          35.29321,
          32.78892
        ]
      },
      "properties": {
        "name": "Dimnah / Horbat Rumah",
        "description": "another name for Rimmon 3",
        "styleUrl": "#landpoint",
        "icon-scale": 0.75,
        "icon": "https://maps.google.com/mapfiles/kml/paddle/red-circle.png"
      }
    },
    {
      "type": "Feature",
      "geometry": {
        "type": "Point",
        "coordinates": [
          35.256944,
          32.785556
        ]
      },
      "properties": {
        "name": "Dimnah / Tel Hanaton",
        "description": "another name for Rimmon 3",
        "styleUrl": "#landpoint",
        "icon-scale": 0.75,
        "icon": "https://maps.google.com/mapfiles/kml/paddle/red-circle.png"
      }
    },
    {
      "type": "Feature",
      "geometry": {
        "type": "Point",
        "coordinates": [
          35.310556,
          32.788056
        ]
      },
      "properties": {
        "name": "Dimnah / Rumana",
        "styleUrl": "#landpoint",
        "icon-scale": 0.75,
        "icon": "https://maps.google.com/mapfiles/kml/paddle/red-circle.png"
      }
    }
  ]
}