{
  "type": "FeatureCollection",
  "features": [
    {
      "type": "Feature",
      "geometry": {
        "type": "Point",
        "coordinates": [
          34.953019,
          31.642074
        ]
      },
      "properties": {
        "name": "Chezib / Tel el Beida",
        "description": "another name for Achzib 1",
        "styleUrl": "#landpoint",
        "icon-scale": 0.75,
        "icon": "https://maps.google.com/mapfiles/kml/paddle/red-circle.png"
      }
    },
    {
      "type": "Feature",
      "geometry": {
        "type": "Point",
        "coordinates": [
          35.003282,
          31.690129
        ]
      },
      "properties": {
        "name": "Chezib / Ain Kezbeh",
        "description": "another name for Achzib 1",
        "styleUrl": "#landpoint",
        "icon-scale": 0.75,
        "icon": "https://maps.google.com/mapfiles/kml/paddle/red-circle.png"
      }
    }
  ]
}