{
  "type": "FeatureCollection",
  "features": [
    {
      "type": "Feature",
      "geometry": {
        "type": "Point",
        "coordinates": [
          36.38715,
          34.39674
        ]
      },
      "properties": {
        "name": "Riblah 2 / Hermel",
        "styleUrl": "#landpoint",
        "icon-scale": 0.75,
        "icon": "https://maps.google.com/mapfiles/kml/paddle/red-circle.png"
      }
    },
    {
      "type": "Feature",
      "geometry": {
        "type": "Point",
        "coordinates": [
          36.366111,
          33.536944
        ]
      },
      "properties": {
        "name": "Riblah 2 / Arbin",
        "styleUrl": "#landpoint",
        "icon-scale": 0.75,
        "icon": "https://maps.google.com/mapfiles/kml/paddle/red-circle.png"
      }
    },
    {
      "type": "Feature",
      "geometry": {
        "type": "Point",
        "coordinates": [
          35.847589,
          32.558661
        ]
      },
      "properties": {
        "name": "Riblah 2 / Tall Irbid",
        "styleUrl": "#landpoint",
        "icon-scale": 0.75,
        "icon": "https://maps.google.com/mapfiles/kml/paddle/red-circle.png"
      }
    },
    {
      "type": "Feature",
      "geometry": {
        "type": "Point",
        "coordinates": [
          36.572623,
          34.459547
        ]
      },
      "properties": {
        "name": "Riblah 2 / Rableh",
        "description": "another name for Riblah 1",
        "styleUrl": "#landpoint",
        "icon-scale": 0.75,
        "icon": "https://maps.google.com/mapfiles/kml/paddle/red-circle.png"
      }
    }
  ]
}