{
  "type": "FeatureCollection",
  "features": [
    {
      "type": "Feature",
      "geometry": {
        "type": "Point",
        "coordinates": [
          35.0965,
          29.85878
        ]
      },
      "properties": {
        "name": "Et Taba",
        "styleUrl": "#waterpoint",
        "icon-scale": 0.75,
        "icon": "https://maps.google.com/mapfiles/kml/paddle/blu-circle.png"
      }
    }
  ]
}