{
  "type": "FeatureCollection",
  "features": [
    {
      "type": "Feature",
      "geometry": {
        "type": "Point",
        "coordinates": [
          34.43891,
          30.74704
        ]
      },
      "properties": {
        "name": "Jebel es Sabha",
        "styleUrl": "#landpoint",
        "icon-scale": 0.75,
        "icon": "https://maps.google.com/mapfiles/kml/paddle/red-circle.png"
      }
    }
  ]
}